ka3005p-0.5.0.dist-info/METADATA
ka3005p-0.5.0.dist-info/WHEEL
ka3005p-0.5.0.dist-info/license_files/LICENSE
ka3005p-0.5.0.dist-info/license_files/LICENSE-APACHE
ka3005p/__init__.py
ka3005p/ka3005p.cp39-win32.pyd
ka3005p-0.5.0.dist-info/RECORD
