Metadata-Version: 2.3
Name: ka3005p
Version: 0.5.0
Classifier: Development Status :: 4 - Beta
Classifier: Programming Language :: Rust
Classifier: Programming Language :: Python :: Implementation :: CPython
Classifier: Programming Language :: Python :: Implementation :: PyPy
Classifier: License :: OSI Approved :: MIT License
Classifier: License :: OSI Approved :: Apache Software License
Classifier: Topic :: System :: Hardware :: Universal Serial Bus (USB) :: Miscellaneous
Requires-Dist: pytest ; extra == 'dev'
Requires-Dist: maturin-import-hook ; extra == 'dev'
Provides-Extra: dev
License-File: LICENSE
License-File: LICENSE-APACHE
Summary: TBD
Keywords: power-supply,remote-control,serial,ka3000,ka3005p
Home-Page: https://github.com/Nicoretti/ka3005p
Author: Nicola Coretti <nico.coretti@gmail.com>, Daniel Hartig <daniel-hartig@gmx.de>, Jack Newman <Jack.Newman12@gmail.com>
Author-email: Nicola Coretti <nico.coretti@gmail.com>, Daniel Hartig <daniel-hartig@gmx.de>, Jack Newman <Jack.Newman12@gmail.com>
Maintainer-email: Nicola Coretti <nico.coretti@gmail.com>
License: MIT OR Apache-2.0
Requires-Python: >=3.8
Project-URL: Source Code, https://github.com/Nicoretti/ka3005p
